convert_list/__init__.py
convert_list-0.0.1.dist-info/LICENSE
convert_list-0.0.1.dist-info/METADATA
convert_list-0.0.1.dist-info/WHEEL
convert_list-0.0.1.dist-info/top_level.txt
convert_list-0.0.1.dist-info/RECORD
