Metadata-Version: 2.1
Name: convert-list
Version: 0.0.1
Summary: Base for list with item conversion.
Home-page: https://dsbowen.github.io/convert-list/
Author: Dillon Bowen
Author-email: dsbowen@wharton.upenn.edu
License: UNKNOWN
Platform: UNKNOWN
Classifier: Programming Language :: Python :: 3
Classifier: License :: OSI Approved :: MIT License
Classifier: Operating System :: OS Independent
Requires-Python: >=3.6
